smart_settings/__init__.py
smart_settings/add_key.py
smart_settings/change_key.py
smart_settings/dynamic.py
smart_settings/file_editing.py
smart_settings/param_classes.py
smart_settings/port_cluster_utils_3.py
smart_settings/smart_settings.py
smart_settings/utils.py
al_smart_settings-1.2.0.dist-info/METADATA
al_smart_settings-1.2.0.dist-info/WHEEL
al_smart_settings-1.2.0.dist-info/licenses/LICENSE
al_smart_settings-1.2.0.dist-info/licenses/LICENSE~
al_smart_settings-1.2.0.dist-info/RECORD
