Metadata-Version: 2.3
Name: al-smart-settings
Version: 1.2.0
Summary: Smart setting files
Project-URL: Source, https://github.com/martius-lab/smart-settings
Project-URL: Bug Tracker, https://github.com/martius-lab/smart-settings/issues
Author: Sebastian Blaes, Marin Vlastelica, Felix Kloss
Author-email: Michal Rolinek <michalrolinek@gmail.com>
Maintainer: Autonomous Learning Group @ University of Tübingen
License-Expression: MIT
License-File: LICENSE
License-File: LICENSE~
Classifier: Development Status :: 5 - Production/Stable
Classifier: License :: OSI Approved :: MIT License
Classifier: Programming Language :: Python :: 3
Requires-Dist: pyyaml
Requires-Dist: tomli; python_version < '3.11'
